Metadata-Version: 2.1
Name: fast-elm-kernel
Version: 1.2
Summary: Extreme Learning Machine kernels for ML
Home-page: UNKNOWN
License: UNKNOWN
Platform: UNKNOWN
License-File: LICENSE
